{
  "Routes": [
    {
      "DownstreamPathTemplate": "/{everything}",
      "DownstreamScheme": "https",
      "DownstreamHostAndPorts": [
        {
          "Host": "family.cagnaz.com",
          "Port": 443
        }
      ],
      "UpstreamPathTemplate": "/family/{everything}",
      "UpstreamHttpMethod": [ "GET", "POST", "PUT", "DELETE" ]
    },
    {
      "DownstreamPathTemplate": "/{everything}",
      "DownstreamScheme": "https",
      "DownstreamHostAndPorts": [
        {
          "Host": "babymonitor.cagnaz.com",
          "Port": 443
        }
      ],
      "UpstreamPathTemplate": "/babymonitor/{everything}",
      "UpstreamHttpMethod": [ "GET", "POST", "PUT", "DELETE" ]
    },
    {
      "DownstreamPathTemplate": "/{everything}",
      "DownstreamScheme": "https",
      "DownstreamHostAndPorts": [
        {
          "Host": "auth.cagnaz.com",
          "Port": 443
        }
      ],
      "UpstreamPathTemplate": "/auth/{everything}",
      "UpstreamHttpMethod": [ "GET", "POST", "PUT", "DELETE" ]
    }
  ],
  "GlobalConfiguration": {
    "BaseUrl": "https://gateway.cagnaz.com"
  }
}